MANIFEST.in
README.md
setup.py
test.py
validfilter/__init__.py
validfilter.egg-info/PKG-INFO
validfilter.egg-info/SOURCES.txt
validfilter.egg-info/dependency_links.txt
validfilter.egg-info/top_level.txt